airflow_valohai_plugin/__init__.py
airflow_valohai_plugin/valohai_plugin.py
airflow_valohai_plugin/hooks/__init__.py
airflow_valohai_plugin/hooks/valohai_hook.py
airflow_valohai_plugin/operators/__init__.py
airflow_valohai_plugin/operators/valohai_download_execution_outputs_operator.py
airflow_valohai_plugin/operators/valohai_submit_execution_operator.py
airflow_valohai_plugin-0.1.0.dist-info/LICENSE
airflow_valohai_plugin-0.1.0.dist-info/METADATA
airflow_valohai_plugin-0.1.0.dist-info/WHEEL
airflow_valohai_plugin-0.1.0.dist-info/entry_points.txt
airflow_valohai_plugin-0.1.0.dist-info/top_level.txt
airflow_valohai_plugin-0.1.0.dist-info/RECORD
