Metadata-Version: 2.1
Name: airflow-valohai-plugin
Version: 0.1.0
Summary: Airflow plugin to launch Valohai executions from Airflow tasks
Home-page: UNKNOWN
Author: Skillup
Author-email: arimbr@gmail.com
License: MIT
Platform: UNKNOWN
